admin_plus/__init__.py
admin_plus/apps.py
admin_plus/mixins.py
admin_plus/settings.py
admin_plus/views.py
admin_plus/filters/__init__.py
admin_plus/filters/date_range.py
admin_plus/filters/default.py
admin_plus/filters/forms.py
admin_plus/filters/numeric_range.py
admin_plus/utils/__init__.py
admin_plus/utils/debug.py
django_admin_plus-0.0.1a1.dist-info/LICENSE
django_admin_plus-0.0.1a1.dist-info/METADATA
django_admin_plus-0.0.1a1.dist-info/WHEEL
django_admin_plus-0.0.1a1.dist-info/top_level.txt
django_admin_plus-0.0.1a1.dist-info/RECORD
