Metadata-Version: 2.1
Name: django-admin-plus
Version: 0.0.1a1
Summary: Django admin panel extension.
Home-page: https://github.com/insspb/django-admin-plus
Author: Andrey Shpak
Author-email: ashpak@ashpak.ru
License: MIT
Project-URL: Docs, https://django-admin-plus.readthedocs.io/
Project-URL: Source, https://github.com/insspb/django-admin-plus
Keywords: django,django-filters,django-admin,django-admin-plus
Platform: any
Classifier: Development Status :: 1 - Planning
Classifier: Natural Language :: English
Classifier: License :: OSI Approved :: MIT License
Classifier: Environment :: Web Environment
Classifier: Framework :: Django
Classifier: Framework :: Django :: 3.0
Classifier: Framework :: Django :: 3.1
Classifier: Framework :: Django :: 3.2
Classifier: Intended Audience :: Developers
Classifier: Operating System :: OS Independent
Classifier: Topic :: Utilities
Classifier: Programming Language :: Python
Classifier: Programming Language :: Python :: 3
Classifier: Programming Language :: Python :: 3 :: Only
Classifier: Programming Language :: Python :: 3.7
Classifier: Programming Language :: Python :: 3.8
Classifier: Programming Language :: Python :: 3.9
Classifier: Programming Language :: Python :: 3.10
Classifier: Programming Language :: Python :: Implementation :: CPython
Requires-Python: >=3.7
Requires-Dist: django (>=3.0)
